gmdata-3.0.2.data/purelib/gmdata-3.0.2-py2.7-nspkg.pth
gmdata-3.0.2.data/purelib/gmdata/__version__.py
gmdata-3.0.2.data/purelib/gmdata/callback.py
gmdata-3.0.2.data/purelib/gmdata/constant.py
gmdata-3.0.2.data/purelib/gmdata/enum.py
gmdata-3.0.2.data/purelib/gmdata/pb_to_dict.py
gmdata-3.0.2.data/purelib/gmdata/retrying.py
gmdata-3.0.2.data/purelib/gmdata/utils.py
gmdata-3.0.2.data/purelib/gmdata/api/__init__.py
gmdata-3.0.2.data/purelib/gmdata/api/basic.py
gmdata-3.0.2.data/purelib/gmdata/api/query.py
gmdata-3.0.2.data/purelib/gmdata/csdk/__init__.py
gmdata-3.0.2.data/purelib/gmdata/csdk/c_sdk.pyd
gmdata-3.0.2.data/purelib/gmdata/csdk/c_sdk.pyi
gmdata-3.0.2.data/purelib/gmdata/csdk/gmdata.dll
gmdata-3.0.2.data/purelib/gmdata/csdk/setup.py
gmdata-3.0.2.data/purelib/gmdata/csdk/setup_linux.py
gmdata-3.0.2.data/purelib/gmdata/model/__init__.py
gmdata-3.0.2.data/purelib/gmdata/model/fundamental.py
gmdata-3.0.2.data/purelib/gmdata/model/history.py
gmdata-3.0.2.data/purelib/gmdata/model/storage.py
gmdata-3.0.2.data/purelib/gmdata/pb/__init__.py
gmdata-3.0.2.data/purelib/gmdata/pb/common_pb2.py
gmdata-3.0.2.data/purelib/gmdata/pb/common_pb2.pyi
gmdata-3.0.2.data/purelib/gmdata/pb/data_pb2.py
gmdata-3.0.2.data/purelib/gmdata/pb/data_pb2.pyi
gmdata-3.0.2.data/purelib/gmdata/pb/fundamental_pb2.py
gmdata-3.0.2.data/purelib/gmdata/pb/fundamental_pb2.pyi
gmdata-3.0.2.data/purelib/gmdata/pb/fundamental_pb2_grpc.py
gmdata-3.0.2.data/purelib/gmdata/pb/fundamental_pb2_grpc.pyi
gmdata-3.0.2.data/purelib/gmdata/pb/history_pb2.py
gmdata-3.0.2.data/purelib/gmdata/pb/history_pb2.pyi
gmdata-3.0.2.data/purelib/gmdata/pb/history_pb2_grpc.py
gmdata-3.0.2.data/purelib/gmdata/pb/history_pb2_grpc.pyi
gmdata-3.0.2.dist-info/METADATA
gmdata-3.0.2.dist-info/RECORD
gmdata-3.0.2.dist-info/WHEEL
gmdata-3.0.2.dist-info/namespace_packages.txt
gmdata-3.0.2.dist-info/top_level.txt
