Metadata-Version: 2.1
Name: gmdata
Version: 3.0.2
Summary: 掘金量化 掘金3 数据sdk
Home-page: http://myquant.cn/
Author: myquant_dev
Author-email: support@myquant.cn
License: Apache 2.0
Platform: UNKNOWN
Classifier: Programming Language :: Python :: 2.7
Classifier: Programming Language :: Python :: 3.6
Classifier: Programming Language :: Python :: 3.7
Requires-Python: >=2.7, !=3.0.*, !=3.1.*, !=3.2.*, !=3.3.*, !=3.4.*, !=3.5.*, <4
Provides-Extra: pandas
Requires-Dist: typing (>=3.6.2)
Requires-Dist: python-dateutil (>=2.7.3)
Requires-Dist: arrow (>=0.12.1)
Requires-Dist: grpcio (>=1.17.1)
Requires-Dist: Cython (>=0.26.1)
Requires-Dist: protobuf (>=3.6.0)
Requires-Dist: pandas (>=0.23.0)
Requires-Dist: attrs (>=18.1.0)
Provides-Extra: pandas
Requires-Dist: pandas; extra == 'pandas'
